enty/__init__.py
enty/entity.py
enty/utils.py
enty/version.py
enty-0.1.5.dist-info/licenses/LICENSE
enty-0.1.5.dist-info/METADATA
enty-0.1.5.dist-info/WHEEL
enty-0.1.5.dist-info/top_level.txt
enty-0.1.5.dist-info/RECORD
