Metadata-Version: 2.4
Name: enty
Version: 0.1.5
Summary: A lightweight ORM with a simple interface.
Author-email: Stelios Papadopoulos <stelios@spapa.us>
License: GNU LESSER GENERAL PUBLIC LICENSE
Project-URL: Homepage, https://github.com/atlab/enty
Requires-Python: >=3.7
License-File: LICENSE
Requires-Dist: pandas
Dynamic: license-file
